broke/__init__.py
broke/cli.py
broke-0.1.1.dist-info/DESCRIPTION.rst
broke-0.1.1.dist-info/METADATA
broke-0.1.1.dist-info/RECORD
broke-0.1.1.dist-info/WHEEL
broke-0.1.1.dist-info/entry_points.txt
broke-0.1.1.dist-info/metadata.json
broke-0.1.1.dist-info/top_level.txt
