Metadata-Version: 2.0
Name: broke
Version: 0.1.1
Summary: Broke: Smooth broken link checker for git repositories
Home-page: http://github.com/KonduitAI/broke
Author: Max Pumperla
Author-email: max.pumperla@googlemail.com
License: MIT
Download-URL: https://github.com/KonduitAI/broke/tarball/0.1.1
Platform: UNKNOWN
Classifier: Development Status :: 3 - Alpha
Classifier: Intended Audience :: Developers
Classifier: Environment :: Console
Classifier: License :: OSI Approved :: Apache Software License
Classifier: Operating System :: OS Independent
Classifier: Programming Language :: Python
Classifier: Programming Language :: Python :: 2
Classifier: Programming Language :: Python :: 3
Requires-Dist: requests
Requires-Dist: click
